ysml/__init__.py
ysml-0.0.1.dist-info/LICENSE
ysml-0.0.1.dist-info/METADATA
ysml-0.0.1.dist-info/WHEEL
ysml-0.0.1.dist-info/top_level.txt
ysml-0.0.1.dist-info/RECORD
